lucent/__init__.py
lucent/util.py
lucent/misc/__init__.py
lucent/misc/channel_reducer.py
lucent/misc/io/__init__.py
lucent/misc/io/collapse_channels.py
lucent/misc/io/serialize_array.py
lucent/misc/io/showing.py
lucent/modelzoo/__init__.py
lucent/modelzoo/util.py
lucent/modelzoo/inceptionv1/InceptionV1.py
lucent/modelzoo/inceptionv1/__init__.py
lucent/modelzoo/inceptionv1/helper_layers.py
lucent/optvis/__init__.py
lucent/optvis/objectives.py
lucent/optvis/objectives_util.py
lucent/optvis/render.py
lucent/optvis/transform.py
lucent/optvis/param/__init__.py
lucent/optvis/param/color.py
lucent/optvis/param/cppn.py
lucent/optvis/param/gan.py
lucent/optvis/param/images.py
lucent/optvis/param/lowres.py
lucent/optvis/param/resize_bilinear_nd.py
lucent/optvis/param/spatial.py
torch_lucent-0.1.8.dist-info/LICENSE
torch_lucent-0.1.8.dist-info/METADATA
torch_lucent-0.1.8.dist-info/WHEEL
torch_lucent-0.1.8.dist-info/top_level.txt
torch_lucent-0.1.8.dist-info/RECORD
