Metadata-Version: 2.1
Name: torch-lucent
Version: 0.1.8
Summary: Lucid for PyTorch. Collection of infrastructure and tools for research in neural network interpretability.
Home-page: https://github.com/greentfrapp/lucent
Author: The Lucent Authors
Author-email: limsweekiat@gmail.com
License: Apache License 2.0
Keywords: pytorch,tensor,machine learning,neural networks,convolutional neural networks,feature visualization,optimization
Platform: UNKNOWN
Classifier: Development Status :: 2 - Pre-Alpha
Classifier: Intended Audience :: Science/Research
Classifier: Intended Audience :: Education
Classifier: License :: OSI Approved :: Apache Software License
Classifier: Natural Language :: English
Classifier: Programming Language :: Python
Classifier: Programming Language :: Python :: 3
Classifier: Programming Language :: Python :: 3.6
Classifier: Topic :: Scientific/Engineering
Classifier: Topic :: Scientific/Engineering :: Artificial Intelligence
Classifier: Topic :: Scientific/Engineering :: Mathematics
Classifier: Topic :: Scientific/Engineering :: Visualization
Classifier: Topic :: Software Development :: Libraries :: Python Modules
Requires-Dist: torch (>=1.5.0)
Requires-Dist: torchvision
Requires-Dist: kornia (<=0.4.1)
Requires-Dist: tqdm
Requires-Dist: numpy
Requires-Dist: ipython
Requires-Dist: pillow
Requires-Dist: future
Requires-Dist: decorator
Requires-Dist: pytest
Requires-Dist: pytest-mock
Requires-Dist: coverage
Requires-Dist: coveralls
Requires-Dist: scikit-learn
